apod/__init__.py
apod/apod_image.py
apod/apod_web.py
apod/exceptions.py
apod-0.1.0.dist-info/LICENSE
apod-0.1.0.dist-info/WHEEL
apod-0.1.0.dist-info/METADATA
apod-0.1.0.dist-info/RECORD
