Metadata-Version: 2.1
Name: apod
Version: 0.1.0
Summary: The apod package pretend to create a easy interface to interact with the apod web page. It can download the apod image of the day
Author-email: Juan Carlos Aranda Huecas <juanki0396@gmail.com>
Requires-Python: >=3.6
Classifier: License :: OSI Approved :: MIT License
Requires-Dist: requests
Requires-Dist: Pillow
Requires-Dist: beautifulsoup4
Project-URL: Source, https://github.com/Juanki0396/APOD_wallpaper
